pyamtrack/__init__.py
pyamtrack/libAT.py
pyamtrack/lib/libgslcblas.so.0
pyamtrack/lib/libgsl.so.27
pyamtrack/lib/__init__.py
pyamtrack/lib/_libAT.abi3.so
pyamtrack-0.14.0.dist-info/top_level.txt
pyamtrack-0.14.0.dist-info/METADATA
pyamtrack-0.14.0.dist-info/RECORD
pyamtrack-0.14.0.dist-info/WHEEL
